{
  "gradeName": "一年级下册",
  "units": [
    {
      "unitName": "第三单元",
      "unitDescription": "动植物汉字",
      "lessons": [
        {
          "lessonName": "第5课",
          "lessonTitle": "数字结尾",
          "characters": ["七", "八", "九"],
          "description": "完成数字汉字的学习"
        },
        {
          "lessonName": "第6课",
          "lessonTitle": "自然元素",
          "characters": ["山", "水", "火"],
          "description": "学习自然相关汉字"
        }
      ]
    },
    {
      "unitName": "第四单元",
      "unitDescription": "生活汉字",
      "lessons": [
        {
          "lessonName": "第7课",
          "lessonTitle": "日常用品",
          "characters": ["口", "手", "目"],
          "description": "学习身体部位汉字"
        }
      ]
    }
  ]
}